{"datastore": "local", "version": "1.0", "attempt": 0, "python_version": "3.7.3 (default, Mar 27 2019, 16:54:48) \n[Clang 4.0.1 (tags/RELEASE_401/final)]", "objects": {"_foreach_stack": "4ca058df2ea422cca260c585409d6ac9face7ebe", "_success": "69e77141c3eb7a8c9ce864251d70c02723f29332", "_task_ok": "69e77141c3eb7a8c9ce864251d70c02723f29332", "_transition": "f5f6ac80756b9c93a81efd44e363f2b5a32548e0", "employees": "96df693e862a612ee639488d06102967f0acb584", "name": "ce00d9e621635194d5f2b956549d81ba942214c8", "_current_step": "01b168d0b2c70f906b295772af9efb98b0797cae", "_exception": "f3627f46179fdd95bf0e83101840fd1d71b60e40", "_foreach_num_splits": "f3627f46179fdd95bf0e83101840fd1d71b60e40", "_foreach_var": "f3627f46179fdd95bf0e83101840fd1d71b60e40", "performance": "e70beb3202d78ab1a8dce6f2fc01cd6e13f31453", "surveys": "cc3f640eeceac9cb0e0060481de9abab2ac47a1a"}, "info": {"_foreach_stack": {"size": 6, "type": "<class 'list'>", "encoding": "gzip+pickle-v2"}, "_success": {"size": 4, "type": "<class 'bool'>", "encoding": "gzip+pickle-v2"}, "_task_ok": {"size": 4, "type": "<class 'bool'>", "encoding": "gzip+pickle-v2"}, "_transition": {"size": 29, "type": "<class 'tuple'>", "encoding": "gzip+pickle-v2"}, "employees": {"size": 205136, "type": "<class 'str'>", "encoding": "gzip+pickle-v2"}, "name": {"size": 37, "type": "<class 'str'>", "encoding": "gzip+pickle-v2"}, "_current_step": {"size": 15, "type": "<class 'str'>", "encoding": "gzip+pickle-v2"}, "_exception": {"size": 4, "type": "<class 'NoneType'>", "encoding": "gzip+pickle-v2"}, "_foreach_num_splits": {"size": 4, "type": "<class 'NoneType'>", "encoding": "gzip+pickle-v2"}, "_foreach_var": {"size": 4, "type": "<class 'NoneType'>", "encoding": "gzip+pickle-v2"}, "performance": {"size": 218510, "type": "<class 'pandas.core.frame.DataFrame'>", "encoding": "gzip+pickle-v2"}, "surveys": {"size": 178308, "type": "<class 'pandas.core.frame.DataFrame'>", "encoding": "gzip+pickle-v2"}}}